MANIFEST.in
README.md
VERSION
requirements-dev.txt
requirements.txt
setup.py
bouncer/__init__.py
bouncer/bouncer.py
cgp_bouncer.egg-info/PKG-INFO
cgp_bouncer.egg-info/SOURCES.txt
cgp_bouncer.egg-info/dependency_links.txt
cgp_bouncer.egg-info/requires.txt
cgp_bouncer.egg-info/top_level.txt
cgp_bouncer.egg-info/zip-safe