Metadata-Version: 2.1
Name: cgp-bouncer
Version: 0.1.0
Summary: Simple email whitelist checker backed by the AWS Secrets Manager
Home-page: https://github.com/ucsc-cgp/bouncer
Author: Jesse Brennan
Author-email: brennan@ucsc.edu
License: Apache License 2.0
Keywords: genomics,secret,client,whitelist,NIHDataCommons
Platform: UNKNOWN
Classifier: Development Status :: 3 - Alpha
Classifier: Intended Audience :: Science/Research
Classifier: License :: OSI Approved :: Apache Software License
Classifier: Natural Language :: English
Classifier: Programming Language :: Python :: 3.6
Classifier: Topic :: Scientific/Engineering :: Bio-Informatics
